<annotation>
	<folder>images</folder>
	<filename>CHNCXR_0483_1.png</filename>
	<path>C:\Users\Nils\Documents\Uni\Semester06\Bachelorarbeit\KardiomegalieDetektion-BA\Dataset\data\shenzhen\images\CHNCXR_0483_1.png</path>
	<source>
		<database>Unknown</database>
	</source>
	<size>
		<width>3000</width>
		<height>2943</height>
		<depth>3</depth>
	</size>
	<segmented>0</segmented>
	<object>
		<name>left_lung</name>
		<pose>Unspecified</pose>
		<truncated>0</truncated>
		<difficult>0</difficult>
		<bndbox>
			<xmin>439</xmin>
			<ymin>519</ymin>
			<xmax>1433</xmax>
			<ymax>2087</ymax>
		</bndbox>
	</object>
	<object>
		<name>right_lung</name>
		<pose>Unspecified</pose>
		<truncated>0</truncated>
		<difficult>0</difficult>
		<bndbox>
			<xmin>1687</xmin>
			<ymin>559</ymin>
			<xmax>2611</xmax>
			<ymax>2205</ymax>
		</bndbox>
	</object>
	<object>
		<name>heart</name>
		<pose>Unspecified</pose>
		<truncated>0</truncated>
		<difficult>0</difficult>
		<bndbox>
			<xmin>1304</xmin>
			<ymin>1395</ymin>
			<xmax>2300</xmax>
			<ymax>2082</ymax>
		</bndbox>
	</object>
</annotation>
