<annotation>
	<folder>images</folder>
	<filename>CHNCXR_0590_1.png</filename>
	<path>C:\Users\Nils\Documents\Uni\Semester06\Bachelorarbeit\KardiomegalieDetektion-BA\Dataset\data\shenzhen\images\CHNCXR_0590_1.png</path>
	<source>
		<database>Unknown</database>
	</source>
	<size>
		<width>2427</width>
		<height>2698</height>
		<depth>1</depth>
	</size>
	<segmented>0</segmented>
	<object>
		<name>left_lung</name>
		<pose>Unspecified</pose>
		<truncated>0</truncated>
		<difficult>0</difficult>
		<bndbox>
			<xmin>288</xmin>
			<ymin>334</ymin>
			<xmax>1160</xmax>
			<ymax>2520</ymax>
		</bndbox>
	</object>
	<object>
		<name>right_lung</name>
		<pose>Unspecified</pose>
		<truncated>0</truncated>
		<difficult>0</difficult>
		<bndbox>
			<xmin>1380</xmin>
			<ymin>367</ymin>
			<xmax>2212</xmax>
			<ymax>2560</ymax>
		</bndbox>
	</object>
	<object>
		<name>heart</name>
		<pose>Unspecified</pose>
		<truncated>0</truncated>
		<difficult>0</difficult>
		<bndbox>
			<xmin>950</xmin>
			<ymin>1247</ymin>
			<xmax>1816</xmax>
			<ymax>2158</ymax>
		</bndbox>
	</object>
</annotation>
