<annotation>
	<folder>images</folder>
	<filename>CHNCXR_0499_1.png</filename>
	<path>C:\Users\Nils\Documents\Uni\Semester06\Bachelorarbeit\KardiomegalieDetektion-BA\Dataset\data\shenzhen\images\CHNCXR_0499_1.png</path>
	<source>
		<database>Unknown</database>
	</source>
	<size>
		<width>2442</width>
		<height>2475</height>
		<depth>1</depth>
	</size>
	<segmented>0</segmented>
	<object>
		<name>left_lung</name>
		<pose>Unspecified</pose>
		<truncated>0</truncated>
		<difficult>0</difficult>
		<bndbox>
			<xmin>281</xmin>
			<ymin>273</ymin>
			<xmax>1151</xmax>
			<ymax>1734</ymax>
		</bndbox>
	</object>
	<object>
		<name>right_lung</name>
		<pose>Unspecified</pose>
		<truncated>0</truncated>
		<difficult>0</difficult>
		<bndbox>
			<xmin>1328</xmin>
			<ymin>255</ymin>
			<xmax>2200</xmax>
			<ymax>2211</ymax>
		</bndbox>
	</object>
	<object>
		<name>heart</name>
		<pose>Unspecified</pose>
		<truncated>0</truncated>
		<difficult>0</difficult>
		<bndbox>
			<xmin>914</xmin>
			<ymin>1314</ymin>
			<xmax>1850</xmax>
			<ymax>2124</ymax>
		</bndbox>
	</object>
</annotation>
