<annotation>
	<folder>images</folder>
	<filename>CHNCXR_0291_0.png</filename>
	<path>C:\Users\Nils\Documents\Uni\Semester06\Bachelorarbeit\Data\Datasets\shenzhen\images\CHNCXR_0291_0.png</path>
	<source>
		<database>Unknown</database>
	</source>
	<size>
		<width>2403</width>
		<height>2449</height>
		<depth>1</depth>
	</size>
	<segmented>0</segmented>
	<object>
		<name>left_lung</name>
		<pose>Unspecified</pose>
		<truncated>0</truncated>
		<difficult>0</difficult>
		<bndbox>
			<xmin>309</xmin>
			<ymin>193</ymin>
			<xmax>1088</xmax>
			<ymax>2123</ymax>
		</bndbox>
	</object>
	<object>
		<name>right_lung</name>
		<pose>Unspecified</pose>
		<truncated>0</truncated>
		<difficult>0</difficult>
		<bndbox>
			<xmin>1248</xmin>
			<ymin>179</ymin>
			<xmax>2115</xmax>
			<ymax>2096</ymax>
		</bndbox>
	</object>
	<object>
		<name>heart</name>
		<pose>Unspecified</pose>
		<truncated>0</truncated>
		<difficult>0</difficult>
		<bndbox>
			<xmin>942</xmin>
			<ymin>1274</ymin>
			<xmax>1657</xmax>
			<ymax>2028</ymax>
		</bndbox>
	</object>
</annotation>
