<annotation>
	<folder>images</folder>
	<filename>CHNCXR_0618_1.png</filename>
	<path>C:\Users\Nils\Documents\Uni\Semester06\Bachelorarbeit\KardiomegalieDetektion-BA\Dataset\data\shenzhen\images\CHNCXR_0618_1.png</path>
	<source>
		<database>Unknown</database>
	</source>
	<size>
		<width>2268</width>
		<height>2427</height>
		<depth>1</depth>
	</size>
	<segmented>0</segmented>
	<object>
		<name>left_lung</name>
		<pose>Unspecified</pose>
		<truncated>0</truncated>
		<difficult>0</difficult>
		<bndbox>
			<xmin>186</xmin>
			<ymin>184</ymin>
			<xmax>1061</xmax>
			<ymax>2121</ymax>
		</bndbox>
	</object>
	<object>
		<name>right_lung</name>
		<pose>Unspecified</pose>
		<truncated>0</truncated>
		<difficult>0</difficult>
		<bndbox>
			<xmin>1264</xmin>
			<ymin>265</ymin>
			<xmax>1998</xmax>
			<ymax>2130</ymax>
		</bndbox>
	</object>
	<object>
		<name>heart</name>
		<pose>Unspecified</pose>
		<truncated>0</truncated>
		<difficult>0</difficult>
		<bndbox>
			<xmin>900</xmin>
			<ymin>1215</ymin>
			<xmax>1683</xmax>
			<ymax>1910</ymax>
		</bndbox>
	</object>
</annotation>
